foru/__init__.py
foru/__main__.py
foru/app/__init__.py
foru/app/base.py
foru/app/cli.py
foru/app/foruc.py
foru/app/gui.py
foru/app/server.py
foru/config/__init__.py
foru/config/config.py
foru/config/global_settings.py
foru/config/logger.config
foru/core/__init__.py
foru/core/enum.py
foru/core/lyric.py
foru/core/models.py
foru/core/player.py
foru/providers/__init__.py
foru/providers/base.py
foru/providers/foru_navidrome.py
foru/resource/__init__.py
foru/resource/resources.py
foru/resource/theme/light.xml
foru/resource/theme/main.qss
foru/run.py
foru/ui/__init__.py
foru/ui/album.py
foru/ui/albumlist.py
foru/ui/bottom.py
foru/ui/content.py
foru/ui/control.py
foru/ui/info.py
foru/ui/main.py
foru/ui/models.py
foru/ui/playinglist.py
foru/ui/playlist.py
foru/ui/progress_bar.py
foru/ui/searchtab.py
foru/ui/sidebar.py
foru/ui/songlist.py
foru/ui/vml.py
foru/utils/__init__.py
foru/utils/aio.py
foru/utils/mode.py
foru/utils/show.py
foru-0.1.2.dist-info/METADATA
foru-0.1.2.dist-info/WHEEL
foru-0.1.2.dist-info/entry_points.txt
foru-0.1.2.dist-info/RECORD
